aws_requests_auth-stubs/__init__.pyi
aws_requests_auth-stubs/aws_auth.pyi
aws_requests_auth-stubs/boto_utils.pyi
aws_requests_auth_stubs-0.4.3.2.dist-info/LICENSE
aws_requests_auth_stubs-0.4.3.2.dist-info/METADATA
aws_requests_auth_stubs-0.4.3.2.dist-info/WHEEL
aws_requests_auth_stubs-0.4.3.2.dist-info/top_level.txt
aws_requests_auth_stubs-0.4.3.2.dist-info/RECORD
