Metadata-Version: 2.1
Name: aws-requests-auth-stubs
Version: 0.4.3.2
Summary: PEP 561 stubs for aws-requests-auth
Home-page: https://github.com/YonatanGreenfeld/aws-requests-auth-stubs
Author: Yonatan Greenfeld
Author-email: yonatangreenfeld97@gmail.com
License: MIT
Classifier: License :: OSI Approved :: MIT License
Classifier: Operating System :: OS Independent
Classifier: Programming Language :: Python :: 3.7
Classifier: Programming Language :: Python :: 3.8
Classifier: Programming Language :: Python :: 3.9
Classifier: Programming Language :: Python :: 3.10
Classifier: Typing :: Typed
Requires-Python: >=3.7
License-File: LICENSE
Requires-Dist: aws-requests-auth (>=0.4.3)
Requires-Dist: botocore-stubs (>=1.27.42)
Requires-Dist: types-requests (>=2.25.0)
Requires-Dist: typing-extensions (>=3.7.4) ; python_version < "3.8"
